postal_codes_tools/__init__.py
postal_codes_tools/formats_constants.py
postal_codes_tools/mappers.py
postal_codes_tools/postal_codes.py
postal_codes_tools/tests/__init__.py
postal_codes_tools/tests/test_formats.py
postal_codes_tools/tests/test_mappers.py
postal_codes_tools-1.1.3.dist-info/METADATA
postal_codes_tools-1.1.3.dist-info/WHEEL
postal_codes_tools-1.1.3.dist-info/top_level.txt
postal_codes_tools-1.1.3.dist-info/RECORD
