Metadata-Version: 2.1
Name: postal-codes-tools
Version: 1.1.3
Summary: Library that help working with different postal codes.
Home-page: https://github.com/ricco386/postal-codes-tools
Author: Richard Kellner
Author-email: richard.kellner@nbs.sk
License: MIT
